[
  {
    "id": "1337051101",
    "title": "🚀MARKETERS PRO afiliados hotmart 🔥",
    "username": "MarketersProafiliadoshotmart",
    "participants": 736,
    "keyword": "afiliados hotmart",
    "joined": true,
    "posted": true,
    "foundAt": "2026-04-06T12:58:15.543Z",
    "joinedAt": "2026-04-06T13:04:46.532Z",
    "postedAt": "2026-04-06T13:08:50.934Z"
  },
  {
    "id": "1792037124",
    "title": "Afiliados BRAIP, HOTMART, MONETIZE",
    "username": "suporteafiliadosbraip",
    "participants": 339,
    "keyword": "afiliados hotmart",
    "joined": true,
    "posted": true,
    "foundAt": "2026-04-06T12:58:15.545Z",
    "joinedAt": "2026-04-06T13:05:20.633Z",
    "postedAt": "2026-04-06T13:10:02.402Z"
  },
  {
    "id": "1700565256",
    "title": "KIWIFY AFILIADOS 🥝",
    "username": "venda24hrsmkt",
    "participants": 757,
    "keyword": "afiliados kiwify",
    "joined": true,
    "posted": true,
    "foundAt": "2026-04-06T12:58:30.352Z",
    "joinedAt": "2026-04-06T13:05:54.105Z",
    "postError": "FORBIDDEN"
  },
  {
    "id": "2211660262",
    "title": "Kiwify Afiliados",
    "username": "kiwifyafiliadosinfoprodutos",
    "participants": 48,
    "keyword": "afiliados kiwify",
    "joined": true,
    "posted": true,
    "foundAt": "2026-04-06T12:58:30.352Z",
    "joinedAt": "2026-04-06T13:06:25.395Z",
    "postError": "FORBIDDEN"
  },
  {
    "id": "2112719872",
    "title": "Comunidade Afiliados 💵 (eduzz, ticto, monetizze, kiwify, perfectpay, braip, hotmart)",
    "username": "mastermindafiliados",
    "participants": 31,
    "keyword": "afiliados kiwify",
    "joined": true,
    "posted": false,
    "foundAt": "2026-04-06T12:58:30.369Z",
    "joinedAt": "2026-04-06T13:07:20.475Z"
  },
  {
    "id": "1687272319",
    "title": "Kiwify Afiliados e Produtores",
    "username": "kiwifymembros",
    "participants": 133,
    "keyword": "afiliados kiwify",
    "joined": false,
    "posted": false,
    "foundAt": "2026-04-06T12:58:30.369Z"
  },
  {
    "id": "1705757760",
    "title": "Suporte / Afiliados Kiwify 🥝",
    "username": "suporte_afiliados_kiwify",
    "participants": 91,
    "keyword": "afiliados kiwify",
    "joined": false,
    "posted": false,
    "foundAt": "2026-04-06T12:58:30.369Z"
  },
  {
    "id": "2175913868",
    "title": "AFILIADOS - PRIMEIRA VENDA NA KIWIFY",
    "username": "GRUPOVIP24O",
    "participants": 16,
    "keyword": "afiliados kiwify",
    "joined": false,
    "posted": false,
    "foundAt": "2026-04-06T12:58:30.370Z"
  },
  {
    "id": "1700887141",
    "title": "Marketing digital",
    "username": "celularoffmarkenting",
    "participants": 18444,
    "keyword": "marketing digital",
    "joined": false,
    "posted": false,
    "foundAt": "2026-04-06T12:58:40.777Z"
  },
  {
    "id": "2004151693",
    "title": "Digital Networking - Marketing Digital",
    "username": "MarketingDigital_Networking",
    "participants": 4444,
    "keyword": "marketing digital",
    "joined": false,
    "posted": false,
    "foundAt": "2026-04-06T12:58:40.777Z"
  },
  {
    "id": "1745336312",
    "title": "🎯 VENDAS & DIVULGAÇÕES ONLINE 📊🚀📣",
    "username": "minadasdivulgacoesgratis",
    "participants": 607,
    "keyword": "vendas online",
    "joined": false,
    "posted": false,
    "foundAt": "2026-04-06T12:58:54.701Z"
  },
  {
    "id": "1672934785",
    "title": "Vendas Onlines",
    "username": "vendasnainternets",
    "participants": 271,
    "keyword": "vendas online",
    "joined": false,
    "posted": false,
    "foundAt": "2026-04-06T12:58:54.702Z"
  },
  {
    "id": "1983661833",
    "title": "DIVULGAÇÃO DE VENDAS ONLINES🤑",
    "username": "vendason4",
    "participants": 25,
    "keyword": "vendas online",
    "joined": false,
    "posted": false,
    "foundAt": "2026-04-06T12:58:54.733Z"
  },
  {
    "id": "3319823704",
    "title": "🌐💎 Vendas Online VIP 🚀💸",
    "username": "vendas_online055",
    "participants": 4,
    "keyword": "vendas online",
    "joined": false,
    "posted": false,
    "foundAt": "2026-04-06T12:58:54.734Z"
  },
  {
    "id": "1534804543",
    "title": "Renda Extra Oficial 🇧🇷",
    "username": "SuperAI_Brasil",
    "participants": 16414,
    "keyword": "renda extra",
    "joined": false,
    "posted": false,
    "foundAt": "2026-04-06T12:59:09.794Z"
  },
  {
    "id": "1770962243",
    "title": "Cursos Renda Extra",
    "username": "cursosja",
    "participants": 9995,
    "keyword": "renda extra",
    "joined": false,
    "posted": false,
    "foundAt": "2026-04-06T12:59:09.795Z"
  },
  {
    "id": "1521749762",
    "title": "RENDA EXTRA 20253️⃣🇧🇷",
    "username": "APLICATIVO_RENDA_EXTRA_3",
    "participants": 3432,
    "keyword": "renda extra",
    "joined": false,
    "posted": false,
    "foundAt": "2026-04-06T12:59:09.802Z"
  },
  {
    "id": "1891016002",
    "title": "Renda Extra 💸",
    "username": "renda_extra0",
    "participants": 144,
    "keyword": "renda extra",
    "joined": false,
    "posted": false,
    "foundAt": "2026-04-06T12:59:09.803Z"
  },
  {
    "id": "1704603623",
    "title": "Renda_extra$$$",
    "username": "rendas_extra",
    "participants": 53,
    "keyword": "renda extra",
    "joined": false,
    "posted": false,
    "foundAt": "2026-04-06T12:59:09.804Z"
  },
  {
    "id": "2261772939",
    "title": "Empreendedorismo digital",
    "username": "marketinglcdigital",
    "participants": 382,
    "keyword": "empreendedorismo digital",
    "joined": false,
    "posted": false,
    "foundAt": "2026-04-06T12:59:22.811Z"
  },
  {
    "id": "1206028607",
    "title": "Presença Digital - Marketing - Empreendedorismo - Tecnologia",
    "username": "PDBrasilOficial",
    "participants": 222,
    "keyword": "empreendedorismo digital",
    "joined": false,
    "posted": false,
    "foundAt": "2026-04-06T12:59:22.811Z"
  },
  {
    "id": "2211165239",
    "title": "Canal da Juh | Marketing Digital | Empreendedorismo",
    "username": "julianavieira_packstories",
    "participants": 503,
    "keyword": "empreendedorismo digital",
    "joined": false,
    "posted": false,
    "foundAt": "2026-04-06T12:59:22.813Z"
  },
  {
    "id": "1234907524",
    "title": "[CHAT] Agência Alcance Certo",
    "username": "empreendedorismo_digital_brasil",
    "participants": 127,
    "keyword": "empreendedorismo digital",
    "joined": false,
    "posted": false,
    "foundAt": "2026-04-06T12:59:22.813Z"
  },
  {
    "id": "1967233055",
    "title": "Afiliados Shopee Brasil",
    "username": "afiliadosbrasilshopee",
    "participants": 2033,
    "keyword": "afiliados brasil",
    "joined": false,
    "posted": false,
    "foundAt": "2026-04-06T12:59:33.523Z"
  },
  {
    "id": "1559368648",
    "title": "AFILIADOS - Naturance Brasil",
    "username": "naturance",
    "participants": 3032,
    "keyword": "afiliados brasil",
    "joined": false,
    "posted": false,
    "foundAt": "2026-04-06T12:59:33.523Z"
  },
  {
    "id": "2916245089",
    "title": "Shopee Vídeos - Vídeos Afiliados Brasil 🧡",
    "username": "videosafiiadosbrasil",
    "participants": 2285,
    "keyword": "afiliados brasil",
    "joined": false,
    "posted": false,
    "foundAt": "2026-04-06T12:59:33.525Z"
  },
  {
    "id": "2239063045",
    "title": "AFILIADOS SEGREDOS",
    "username": "afiliados_brasil",
    "participants": 7,
    "keyword": "afiliados brasil",
    "joined": false,
    "posted": false,
    "foundAt": "2026-04-06T12:59:33.526Z"
  },
  {
    "id": "1999193288",
    "title": "FÁBRICA DE PLRS _ loja de infoprodutos",
    "username": "fabricadeplrs",
    "participants": 1030,
    "keyword": "infoprodutos",
    "joined": false,
    "posted": false,
    "foundAt": "2026-04-06T12:59:42.883Z"
  },
  {
    "id": "2116228286",
    "title": "📲RECEPÇÃO INFOPRODUTOS",
    "username": "infoprodutosrendaextra",
    "participants": 679,
    "keyword": "infoprodutos",
    "joined": false,
    "posted": false,
    "foundAt": "2026-04-06T12:59:42.884Z"
  },
  {
    "id": "2894497655",
    "title": "Central Renda Extra - Vitrine de Infoprodutos 📲",
    "username": "centralrendaextraplr",
    "participants": 77,
    "keyword": "infoprodutos",
    "joined": false,
    "posted": false,
    "foundAt": "2026-04-06T12:59:42.886Z"
  },
  {
    "id": "1264028435",
    "title": "IMPÉRIO LAB - Produtos Premium (PLR - Infoprodutos)",
    "username": "imperiolabPLR",
    "participants": 387,
    "keyword": "infoprodutos",
    "joined": false,
    "posted": false,
    "foundAt": "2026-04-06T12:59:42.886Z"
  },
  {
    "id": "1384859959",
    "title": "Contabilidade Descomplicada para Infoprodutos",
    "username": "contabilidadeparainfoprodutos",
    "participants": 73,
    "keyword": "infoprodutos",
    "joined": false,
    "posted": false,
    "foundAt": "2026-04-06T12:59:42.887Z"
  },
  {
    "id": "1442561035",
    "title": "Tráfego Pago - Do Iniciante ao Avançado",
    "username": "trafego_pago",
    "participants": 338,
    "keyword": "trafego pago",
    "joined": false,
    "posted": false,
    "foundAt": "2026-04-06T13:00:07.135Z"
  },
  {
    "id": "1778640951",
    "title": "NEGOCIOS DIGITALES 💸",
    "username": "NegociosDigitalesB",
    "participants": 259,
    "keyword": "negocio digital",
    "joined": true,
    "posted": true,
    "foundAt": "2026-04-06T13:00:15.725Z",
    "joinedAt": "2026-04-06T23:58:04.381Z",
    "postedAt": "2026-04-07T00:05:12.957Z"
  },
  {
    "id": "1812792759",
    "title": "Seu Negócio Digital",
    "username": "seunegocioonlinehoje",
    "participants": 155,
    "keyword": "negocio digital",
    "joined": false,
    "posted": false,
    "foundAt": "2026-04-06T13:00:15.726Z"
  },
  {
    "id": "1265175279",
    "title": "Negocio Digital",
    "username": "negocio_digital",
    "participants": 2,
    "keyword": "negocio digital",
    "joined": false,
    "posted": false,
    "foundAt": "2026-04-06T13:00:15.728Z"
  },
  {
    "id": "1419814361",
    "title": "Wilson - Negocios Digitales",
    "username": "Negocios_Digitale",
    "participants": 15,
    "keyword": "negocio digital",
    "joined": false,
    "posted": false,
    "foundAt": "2026-04-06T13:00:15.729Z"
  },
  {
    "id": "2166125787",
    "title": "GANHE DINHEIRO 🎰🇧🇷 ONLINE",
    "username": "emprego_trabalhoa",
    "participants": 31694,
    "keyword": "dinheiro online",
    "joined": true,
    "posted": false,
    "foundAt": "2026-04-06T13:00:25.398Z",
    "joinedAt": "2026-04-06T23:58:57.085Z"
  },
  {
    "id": "2550139790",
    "title": "Ganhe dinheiro online",
    "username": "TecnologiaFanucDiscussionGrou",
    "participants": 324,
    "keyword": "dinheiro online",
    "joined": false,
    "posted": false,
    "foundAt": "2026-04-06T13:00:25.399Z"
  },
  {
    "id": "1687837597",
    "title": "GRUPO DINHEIRO ONLINE",
    "username": "GrupoDinheiroOnline",
    "participants": 1660,
    "keyword": "dinheiro online",
    "joined": true,
    "posted": true,
    "foundAt": "2026-04-06T13:00:25.401Z",
    "joinedAt": "2026-04-07T00:03:06.226Z",
    "postedAt": "2026-04-07T00:04:02.765Z"
  },
  {
    "id": "1619365036",
    "title": "Клиенты на недвижимость",
    "username": "Leads_For_Rieltors",
    "participants": 62,
    "keyword": "leads",
    "joined": false,
    "posted": false,
    "foundAt": "2026-04-06T13:00:38.505Z"
  },
  {
    "id": "1828315288",
    "title": "Desafio de Prospecção 2023",
    "username": "desafioprospeccao",
    "participants": 86,
    "keyword": "prospeccao",
    "joined": false,
    "posted": false,
    "foundAt": "2026-04-06T13:00:52.507Z"
  }
]